[
    {
        "year": "2015",
        "median_slope": 0.0,
        "median_intercept": 0.5882352941176399,
        "countries": [
            {
                "name": "Argentina",
                "x": 0.0,
                "y": -1.9984014443252818e-15
            },
            {
                "name": "Australia",
                "x": 1.818181818181817,
                "y": 0.9090909090909121
            },
            {
                "name": "Belgium",
                "x": 0.0,
                "y": -9.992007221626409e-16
            },
            {
                "name": "Brazil",
                "x": 0.0,
                "y": 9.992007221626409e-16
            },
            {
                "name": "China",
                "x": 0.0,
                "y": 9.992007221626409e-16
            },
            {
                "name": "Colombia",
                "x": -1.021405182655144e-14,
                "y": 1.9984014443252818e-15
            },
            {
                "name": "Czech Republic",
                "x": 0.0,
                "y": 1.9984014443252818e-15
            },
            {
                "name": "France",
                "x": 0.0,
                "y": -1.9984014443252818e-15
            },
            {
                "name": "Germany",
                "x": 1.1764705882353,
                "y": 0.5882352941176466
            },
            {
                "name": "Greece",
                "x": 7.86324786324788,
                "y": -1.5628815628815693
            },
            {
                "name": "Israel",
                "x": 0.0,
                "y": 0.0
            },
            {
                "name": "Italy",
                "x": 2.536231884057966,
                "y": -0.517598343685299
            },
            {
                "name": "Kuwait",
                "x": 2.0,
                "y": 1.0000000000000009
            },
            {
                "name": "Mexico",
                "x": 3.157894736842104,
                "y": -1.052631578947369
            },
            {
                "name": "Netherlands",
                "x": 0.0,
                "y": 0.0
            },
            {
                "name": "Philippines",
                "x": 5.0,
                "y": -0.624999999999999
            },
            {
                "name": "Poland",
                "x": 0.5882352941176399,
                "y": 0.7843137254901971
            },
            {
                "name": "Portugal",
                "x": 0.0,
                "y": 9.992007221626409e-16
            },
            {
                "name": "South Africa",
                "x": 4.88768115942029,
                "y": -0.10144927536231896
            },
            {
                "name": "Spain",
                "x": 1.1111111111111098,
                "y": -0.634920634920629
            },
            {
                "name": "Taiwan",
                "x": 0.0,
                "y": 0.0
            },
            {
                "name": "Thailand",
                "x": 8.20423121772447,
                "y": -1.622522072297179
            },
            {
                "name": "Turkey",
                "x": 2.1428571428571423,
                "y": -0.714285714285719
            }
        ]
    },
    {
        "year": "2019",
        "median_slope": 9.992007221626409e-15,
        "median_intercept": 1.1111111111111098,
        "countries": [
            {
                "name": "Argentina",
                "x": 10.33333333333332,
                "y": 2.66666666666666
            },
            {
                "name": "Australia",
                "x": -1.0658141036401503e-14,
                "y": 9.992007221626409e-15
            },
            {
                "name": "Belgium",
                "x": 0.0,
                "y": -9.992007221626409e-15
            },
            {
                "name": "Brazil",
                "x": 5.555555555555539,
                "y": 9.992007221626409e-15
            },
            {
                "name": "China",
                "x": 1.1111111111111098,
                "y": 0.55555555555556
            },
            {
                "name": "Colombia",
                "x": -3.019806626980426e-14,
                "y": 0.0
            },
            {
                "name": "Czech Republic",
                "x": -1.9539925233402755e-14,
                "y": 9.992007221626409e-15
            },
            {
                "name": "France",
                "x": 0.0,
                "y": -9.992007221626409e-15
            },
            {
                "name": "Germany",
                "x": 0.8823529411764799,
                "y": 1.176470588235289
            },
            {
                "name": "Greece",
                "x": 14.285714285714299,
                "y": 7.14285714285713
            },
            {
                "name": "Israel",
                "x": -1.0658141036401503e-14,
                "y": 0.0
            },
            {
                "name": "Italy",
                "x": 4.464285714285699,
                "y": 1.7361111111111154
            },
            {
                "name": "Kuwait",
                "x": 6.0931899641577,
                "y": 1.935483870967745
            },
            {
                "name": "Mexico",
                "x": 3.3333333333333197,
                "y": 1.6666666666666643
            },
            {
                "name": "Netherlands",
                "x": -1.0658141036401503e-14,
                "y": 0.0
            },
            {
                "name": "Philippines",
                "x": 9.42783094098883,
                "y": -0.05582137161084999
            },
            {
                "name": "Poland",
                "x": 2.45098039215684,
                "y": -0.5882352941176399
            },
            {
                "name": "Portugal",
                "x": 0.0,
                "y": 0.0
            },
            {
                "name": "South Africa",
                "x": 5.15151515151515,
                "y": -0.6439393939394
            },
            {
                "name": "Spain",
                "x": 0.7692307692307594,
                "y": 0.38461538461539013
            },
            {
                "name": "Taiwan",
                "x": -1.0658141036401503e-14,
                "y": 0.0
            },
            {
                "name": "Thailand",
                "x": 11.1111111111111,
                "y": 0.0
            },
            {
                "name": "Turkey",
                "x": 1.42857142857142,
                "y": 1.904761904761902
            }
        ]
    },
    {
        "year": "2018",
        "median_slope": 0.2941176470588198,
        "median_intercept": 1.07843137254903,
        "countries": [
            {
                "name": "Argentina",
                "x": 5.666666666666667,
                "y": 4.5
            },
            {
                "name": "Australia",
                "x": 1.2121212121212093,
                "y": -0.9090909090909003
            },
            {
                "name": "Belgium",
                "x": 9.769962616701378e-15,
                "y": 0.0
            },
            {
                "name": "Brazil",
                "x": 3.3333333333333295,
                "y": 1.6666666666666718
            },
            {
                "name": "China",
                "x": 0.5555555555555598,
                "y": 0.7407407407407498
            },
            {
                "name": "Colombia",
                "x": -2.042810365310288e-14,
                "y": 0.0
            },
            {
                "name": "Czech Republic",
                "x": -1.0658141036401503e-14,
                "y": 9.769962616701378e-15
            },
            {
                "name": "France",
                "x": 9.769962616701378e-15,
                "y": -1.021405182655144e-14
            },
            {
                "name": "Germany",
                "x": 1.07843137254903,
                "y": 0.2941176470588198
            },
            {
                "name": "Greece",
                "x": 8.62433862433862,
                "y": 8.41269841269841
            },
            {
                "name": "Israel",
                "x": -1.0658141036401503e-14,
                "y": 9.769962616701378e-15
            },
            {
                "name": "Italy",
                "x": 2.9110593512767395,
                "y": 1.9461697722567308
            },
            {
                "name": "Kuwait",
                "x": 4.60215053763441,
                "y": 2.247311827956995
            },
            {
                "name": "Mexico",
                "x": 1.6666666666666599,
                "y": 2.2222222222222237
            },
            {
                "name": "Netherlands",
                "x": 0.0,
                "y": 0.0
            },
            {
                "name": "Philippines",
                "x": 7.33452950558214,
                "y": 1.7384370015948978
            },
            {
                "name": "Poland",
                "x": 2.3725490196078396,
                "y": -0.2843137254901902
            },
            {
                "name": "Portugal",
                "x": 0.0,
                "y": 0.0
            },
            {
                "name": "South Africa",
                "x": 4.886363636363639,
                "y": -0.3030303030303001
            },
            {
                "name": "Spain",
                "x": 0.3846153846153797,
                "y": 0.5128205128205199
            },
            {
                "name": "Taiwan",
                "x": 0.0,
                "y": 0.0
            },
            {
                "name": "Thailand",
                "x": 8.04597701149425,
                "y": 2.2988505747126466
            },
            {
                "name": "Turkey",
                "x": 0.47619047619047983,
                "y": 1.42857142857143
            }
        ]
    },
    {
        "year": "2016",
        "median_slope": 0.0,
        "median_intercept": 0.8333333333333401,
        "countries": [
            {
                "name": "Argentina",
                "x": 0.8333333333333401,
                "y": 2.5
            },
            {
                "name": "Australia",
                "x": 2.727272727272724,
                "y": -0.9090909090908998
            },
            {
                "name": "Belgium",
                "x": 0.0,
                "y": 0.0
            },
            {
                "name": "Brazil",
                "x": 0.5555555555555602,
                "y": 1.666666666666669
            },
            {
                "name": "China",
                "x": 0.0,
                "y": 0.0
            },
            {
                "name": "Colombia",
                "x": -9.769962616701378e-15,
                "y": 0.0
            },
            {
                "name": "Czech Republic",
                "x": 0.0,
                "y": 9.992007221626409e-15
            },
            {
                "name": "France",
                "x": 0.0,
                "y": 0.0
            },
            {
                "name": "Germany",
                "x": 1.76470588235295,
                "y": -0.5882352941176401
            },
            {
                "name": "Greece",
                "x": 7.03296703296704,
                "y": -3.5653235653235598
            },
            {
                "name": "Israel",
                "x": 0.0,
                "y": 0.0
            },
            {
                "name": "Italy",
                "x": 2.494824016563146,
                "y": -0.4347826086956501
            },
            {
                "name": "Kuwait",
                "x": 3.2222222222222223,
                "y": -0.33333333333332993
            },
            {
                "name": "Mexico",
                "x": 2.456140350877194,
                "y": -1.40350877192982
            },
            {
                "name": "Netherlands",
                "x": 0.0,
                "y": 0.0
            },
            {
                "name": "Philippines",
                "x": 4.58333333333333,
                "y": 1.250000000000002
            },
            {
                "name": "Poland",
                "x": 1.34313725490196,
                "y": 1.0882352941176514
            },
            {
                "name": "Portugal",
                "x": 0.0,
                "y": 0.0
            },
            {
                "name": "South Africa",
                "x": 5.15085638998683,
                "y": 0.579380764163375
            },
            {
                "name": "Spain",
                "x": 0.6349206349206402,
                "y": -0.47619047619047006
            },
            {
                "name": "Taiwan",
                "x": 0.0,
                "y": 0.0
            },
            {
                "name": "Thailand",
                "x": 8.21455938697318,
                "y": -0.1455938697318
            },
            {
                "name": "Turkey",
                "x": 1.66666666666667,
                "y": -0.9523809523809499
            }
        ]
    },
    {
        "year": "2017",
        "median_slope": 1.021405182655144e-14,
        "median_intercept": 1.3725490196078498,
        "countries": [
            {
                "name": "Argentina",
                "x": 2.5,
                "y": 3.3333333333333304
            },
            {
                "name": "Australia",
                "x": 2.1212121212121198,
                "y": -1.2121212121212097
            },
            {
                "name": "Belgium",
                "x": 0.0,
                "y": 0.0
            },
            {
                "name": "Brazil",
                "x": 1.6666666666666599,
                "y": 2.2222222222222263
            },
            {
                "name": "China",
                "x": 0.18518518518518956,
                "y": 0.5555555555555602
            },
            {
                "name": "Colombia",
                "x": -1.0658141036401503e-14,
                "y": 0.0
            },
            {
                "name": "Czech Republic",
                "x": -1.0658141036401503e-14,
                "y": 1.021405182655144e-14
            },
            {
                "name": "France",
                "x": 0.0,
                "y": -9.769962616701378e-15
            },
            {
                "name": "Germany",
                "x": 1.3725490196078498,
                "y": -0.7843137254901897
            },
            {
                "name": "Greece",
                "x": 5.999185999186009,
                "y": 4.89214489214489
            },
            {
                "name": "Israel",
                "x": 0.0,
                "y": 1.021405182655144e-14
            },
            {
                "name": "Italy",
                "x": 1.9371118012422297,
                "y": 0.9976708074534202
            },
            {
                "name": "Kuwait",
                "x": 3.6451612903225787,
                "y": 1.491039426523304
            },
            {
                "name": "Mexico",
                "x": 1.9590643274853798,
                "y": 0.6140350877193002
            },
            {
                "name": "Netherlands",
                "x": 0.0,
                "y": 0.0
            },
            {
                "name": "Philippines",
                "x": 5.71969696969697,
                "y": 2.5757575757575792
            },
            {
                "name": "Poland",
                "x": 2.26470588235294,
                "y": 0.07843137254902022
            },
            {
                "name": "Portugal",
                "x": 0.0,
                "y": 0.0
            },
            {
                "name": "South Africa",
                "x": 5.238801054018445,
                "y": -0.47266139657443995
            },
            {
                "name": "Spain",
                "x": 0.12820512820512953,
                "y": 0.38461538461539013
            },
            {
                "name": "Taiwan",
                "x": 0.0,
                "y": 0.0
            },
            {
                "name": "Thailand",
                "x": 7.524904214559379,
                "y": 1.731800766283531
            },
            {
                "name": "Turkey",
                "x": 0.9523809523809499,
                "y": -0.71428571428571
            }
        ]
    },
    {
        "year": "2014",
        "median_slope": 1.9984014443252818e-15,
        "median_intercept": 0.19607843137253989,
        "countries": [
            {
                "name": "Argentina",
                "x": 0.0,
                "y": -9.992007221626409e-16
            },
            {
                "name": "Australia",
                "x": 0.909090909090906,
                "y": 1.212121212121215
            },
            {
                "name": "Belgium",
                "x": 0.0,
                "y": -9.992007221626409e-16
            },
            {
                "name": "Brazil",
                "x": 0.0,
                "y": 1.9984014443252818e-15
            },
            {
                "name": "China",
                "x": 0.0,
                "y": 1.9984014443252818e-15
            },
            {
                "name": "Colombia",
                "x": -9.992007221626409e-15,
                "y": 9.992007221626409e-16
            },
            {
                "name": "Czech Republic",
                "x": -9.992007221626409e-15,
                "y": 1.9984014443252818e-15
            },
            {
                "name": "France",
                "x": 0.0,
                "y": -2.9976021664879227e-15
            },
            {
                "name": "Germany",
                "x": 0.5882352941176499,
                "y": 0.7843137254901951
            },
            {
                "name": "Greece",
                "x": 7.96092796092797,
                "y": 0.05291005291004902
            },
            {
                "name": "Israel",
                "x": 0.0,
                "y": 1.9984014443252818e-15
            },
            {
                "name": "Italy",
                "x": 2.577639751552789,
                "y": -0.13457556935817405
            },
            {
                "name": "Kuwait",
                "x": 0.999999999999996,
                "y": 1.333333333333335
            },
            {
                "name": "Mexico",
                "x": 3.50877192982456,
                "y": 9.992007221626409e-16
            },
            {
                "name": "Netherlands",
                "x": 0.0,
                "y": 0.0
            },
            {
                "name": "Philippines",
                "x": 5.625,
                "y": -0.833333333333331
            },
            {
                "name": "Poland",
                "x": 0.19607843137253989,
                "y": 0.588235294117648
            },
            {
                "name": "Portugal",
                "x": 0.0,
                "y": 1.9984014443252818e-15
            },
            {
                "name": "South Africa",
                "x": 4.8659420289855095,
                "y": 0.249999999999999
            },
            {
                "name": "Spain",
                "x": 1.428571428571426,
                "y": -0.47619047619047605
            },
            {
                "name": "Taiwan",
                "x": 0.0,
                "y": 9.992007221626409e-16
            },
            {
                "name": "Thailand",
                "x": 8.49341995668832,
                "y": 0.13293353323338403
            },
            {
                "name": "Turkey",
                "x": 2.380952380952378,
                "y": 9.992007221626409e-16
            }
        ]
    }
]