[
    {
        "name": "Argentina",
        "years": [
            {
                "year": 2018,
                "median_slope": -3.237315237315238,
                "median_intercept": 19.83418290854572,
                "x": 33.10906685906685,
                "y": 2.6190476190476297
            },
            {
                "year": 2019,
                "median_slope": -1.157916788352395,
                "median_intercept": 15.03348889465042,
                "x": 34.534632034632,
                "y": 3.5708273208273305
            },
            {
                "year": 2015,
                "median_slope": 0.3958901618476003,
                "median_intercept": 24.5058391900497,
                "x": 39.643785544520796,
                "y": -3.05403474521121
            },
            {
                "year": 2014,
                "median_slope": 0.9132750452692799,
                "median_intercept": 23.42006671089494,
                "x": 40.8903607739393,
                "y": -1.3086484593837402
            },
            {
                "year": 2017,
                "median_slope": -3.5598747657571197,
                "median_intercept": 26.183754218618798,
                "x": 34.01535193201852,
                "y": -1.03234728234727
            },
            {
                "year": 2016,
                "median_slope": -1.41962992792028,
                "median_intercept": 26.61926996832661,
                "x": 37.3330527497194,
                "y": -3.75335698252364
            }
        ]
    },
    {
        "name": "Australia",
        "years": [
            {
                "year": 2018,
                "median_slope": -3.237315237315238,
                "median_intercept": 19.83418290854572,
                "x": 4.201228878648202,
                "y": -2.654889912954418
            },
            {
                "year": 2019,
                "median_slope": -1.157916788352395,
                "median_intercept": 15.03348889465042,
                "x": 0.8730158730157989,
                "y": -0.15873015873015994
            },
            {
                "year": 2015,
                "median_slope": 0.3958901618476003,
                "median_intercept": 24.5058391900497,
                "x": 9.7977972551027,
                "y": 0.3470778992600603
            },
            {
                "year": 2014,
                "median_slope": 0.9132750452692799,
                "median_intercept": 23.42006671089494,
                "x": 8.709978615101999,
                "y": 1.5915183277612188
            },
            {
                "year": 2017,
                "median_slope": -3.5598747657571197,
                "median_intercept": 26.183754218618798,
                "x": 7.332309267793001,
                "y": -3.9631336405529902
            },
            {
                "year": 2016,
                "median_slope": -1.41962992792028,
                "median_intercept": 26.61926996832661,
                "x": 10.3191670933607,
                "y": -3.5279057859703
            }
        ]
    },
    {
        "name": "Belgium",
        "years": [
            {
                "year": 2018,
                "median_slope": -3.237315237315238,
                "median_intercept": 19.83418290854572,
                "x": 12.098076923076901,
                "y": -5.62243589743589
            },
            {
                "year": 2019,
                "median_slope": -1.157916788352395,
                "median_intercept": 15.03348889465042,
                "x": 6.3053418803418,
                "y": -2.518803418803413
            },
            {
                "year": 2015,
                "median_slope": 0.3958901618476003,
                "median_intercept": 24.5058391900497,
                "x": 19.97241596187146,
                "y": 0.6016260856373603
            },
            {
                "year": 2014,
                "median_slope": 0.9132750452692799,
                "median_intercept": 23.42006671089494,
                "x": 18.93671382156991,
                "y": 1.751128304319817
            },
            {
                "year": 2017,
                "median_slope": -3.5598747657571197,
                "median_intercept": 26.183754218618798,
                "x": 17.25653594771231,
                "y": -6.129901960784309
            },
            {
                "year": 2016,
                "median_slope": -1.41962992792028,
                "median_intercept": 26.61926996832661,
                "x": 20.259165181224,
                "y": -3.71663695781342
            }
        ]
    },
    {
        "name": "Brazil",
        "years": [
            {
                "year": 2018,
                "median_slope": -3.237315237315238,
                "median_intercept": 19.83418290854572,
                "x": 31.08155988198959,
                "y": 1.5735612163757202
            },
            {
                "year": 2019,
                "median_slope": -1.157916788352395,
                "median_intercept": 15.03348889465042,
                "x": 31.875466937772998,
                "y": 1.3107578345105
            },
            {
                "year": 2015,
                "median_slope": 0.3958901618476003,
                "median_intercept": 24.5058391900497,
                "x": 31.44664770387144,
                "y": -0.8968519392539198
            },
            {
                "year": 2014,
                "median_slope": 0.9132750452692799,
                "median_intercept": 23.42006671089494,
                "x": 31.754522175002798,
                "y": -0.9016860332649803
            },
            {
                "year": 2017,
                "median_slope": -3.5598747657571197,
                "median_intercept": 26.183754218618798,
                "x": 29.609397787179603,
                "y": 2.01380319508542
            },
            {
                "year": 2016,
                "median_slope": -1.41962992792028,
                "median_intercept": 26.61926996832661,
                "x": 30.75926425576392,
                "y": -1.41962992792028
            }
        ]
    },
    {
        "name": "Canada",
        "years": [
            {
                "year": 2018,
                "median_slope": -3.237315237315238,
                "median_intercept": 19.83418290854572,
                "x": 6.0277777777777,
                "y": -1.1527777777777901
            },
            {
                "year": 2019,
                "median_slope": -1.157916788352395,
                "median_intercept": 15.03348889465042,
                "x": 4.75,
                "y": -0.3333333333333699
            },
            {
                "year": 2015,
                "median_slope": 0.3958901618476003,
                "median_intercept": 24.5058391900497,
                "x": 6.933333333333302,
                "y": 0.9111111111111001
            },
            {
                "year": 2014,
                "median_slope": 0.9132750452692799,
                "median_intercept": 23.42006671089494,
                "x": 6.318518518518498,
                "y": 1.1777777777777698
            },
            {
                "year": 2017,
                "median_slope": -3.5598747657571197,
                "median_intercept": 26.183754218618798,
                "x": 7.699074074074002,
                "y": -1.833333333333353
            },
            {
                "year": 2016,
                "median_slope": -1.41962992792028,
                "median_intercept": 26.61926996832661,
                "x": 7.504629629629601,
                "y": -0.44907407407408373
            }
        ]
    },
    {
        "name": "Chile",
        "years": [
            {
                "year": 2018,
                "median_slope": -3.237315237315238,
                "median_intercept": 19.83418290854572,
                "x": 19.35352304112916,
                "y": -5.72072032853017
            },
            {
                "year": 2019,
                "median_slope": -1.157916788352395,
                "median_intercept": 15.03348889465042,
                "x": 13.01934322986952,
                "y": -1.133903133903134
            },
            {
                "year": 2015,
                "median_slope": 0.3958901618476003,
                "median_intercept": 24.5058391900497,
                "x": 33.7250913793075,
                "y": -0.77440637712284
            },
            {
                "year": 2014,
                "median_slope": 0.9132750452692799,
                "median_intercept": 23.42006671089494,
                "x": 32.917551437642,
                "y": 2.356272078965921
            },
            {
                "year": 2017,
                "median_slope": -3.5598747657571197,
                "median_intercept": 26.183754218618798,
                "x": 27.775098070513973,
                "y": -9.85269832977813
            },
            {
                "year": 2016,
                "median_slope": -1.41962992792028,
                "median_intercept": 26.61926996832661,
                "x": 33.11462762226773,
                "y": -6.64349735657036
            }
        ]
    },
    {
        "name": "China",
        "years": [
            {
                "year": 2018,
                "median_slope": -3.237315237315238,
                "median_intercept": 19.83418290854572,
                "x": 42.8755042811894,
                "y": -9.53150341266747
            },
            {
                "year": 2019,
                "median_slope": -1.157916788352395,
                "median_intercept": 15.03348889465042,
                "x": 35.8682500888876,
                "y": -9.26003600168737
            },
            {
                "year": 2015,
                "median_slope": 0.3958901618476003,
                "median_intercept": 24.5058391900497,
                "x": 38.7063668001799,
                "y": 4.03939490781975
            },
            {
                "year": 2014,
                "median_slope": 0.9132750452692799,
                "median_intercept": 23.42006671089494,
                "x": 37.520991073774994,
                "y": 0.9132750452692799
            },
            {
                "year": 2017,
                "median_slope": -3.5598747657571197,
                "median_intercept": 26.183754218618798,
                "x": 44.3912003903509,
                "y": -2.248542017886622
            },
            {
                "year": 2016,
                "median_slope": -1.41962992792028,
                "median_intercept": 26.61926996832661,
                "x": 40.8789373024776,
                "y": 4.63022778268761
            }
        ]
    },
    {
        "name": "Colombia",
        "years": [
            {
                "year": 2018,
                "median_slope": -3.237315237315238,
                "median_intercept": 19.83418290854572,
                "x": 29.66015066015067,
                "y": -3.237315237315238
            },
            {
                "year": 2019,
                "median_slope": -1.157916788352395,
                "median_intercept": 15.03348889465042,
                "x": 26.79231879231878,
                "y": -2.6061716061716123
            },
            {
                "year": 2015,
                "median_slope": 0.3958901618476003,
                "median_intercept": 24.5058391900497,
                "x": 42.7212822902478,
                "y": -4.3360137325654495
            },
            {
                "year": 2014,
                "median_slope": 0.9132750452692799,
                "median_intercept": 23.42006671089494,
                "x": 45.150723667965195,
                "y": -2.2108633832771702
            },
            {
                "year": 2017,
                "median_slope": -3.5598747657571197,
                "median_intercept": 26.183754218618798,
                "x": 34.7378477378477,
                "y": -4.24972774972776
            },
            {
                "year": 2016,
                "median_slope": -1.41962992792028,
                "median_intercept": 26.61926996832661,
                "x": 38.5693239658757,
                "y": -4.64468181709561
            }
        ]
    },
    {
        "name": "Croatia",
        "years": [
            {
                "year": 2018,
                "median_slope": -3.237315237315238,
                "median_intercept": 19.83418290854572,
                "x": 34.3055555555556,
                "y": 1.52777777777781
            },
            {
                "year": 2019,
                "median_slope": -1.157916788352395,
                "median_intercept": 15.03348889465042,
                "x": 36.8055555555555,
                "y": 1.9984014443252818e-14
            },
            {
                "year": 2015,
                "median_slope": 0.3958901618476003,
                "median_intercept": 24.5058391900497,
                "x": 22.583333333333286,
                "y": 1.22222222222224
            },
            {
                "year": 2014,
                "median_slope": 0.9132750452692799,
                "median_intercept": 23.42006671089494,
                "x": 23.97222222222225,
                "y": -3.4999999999999702
            },
            {
                "year": 2017,
                "median_slope": -3.5598747657571197,
                "median_intercept": 26.183754218618798,
                "x": 27.499999999999922,
                "y": 5.4166666666667
            },
            {
                "year": 2016,
                "median_slope": -1.41962992792028,
                "median_intercept": 26.61926996832661,
                "x": 22.41666666666669,
                "y": 7.666666666666689
            }
        ]
    },
    {
        "name": "Czech Republic",
        "years": [
            {
                "year": 2018,
                "median_slope": -3.237315237315238,
                "median_intercept": 19.83418290854572,
                "x": 16.166666666666643,
                "y": -2.05555555555555
            },
            {
                "year": 2019,
                "median_slope": -1.157916788352395,
                "median_intercept": 15.03348889465042,
                "x": 12.49999999999994,
                "y": 9.992007221626409e-15
            },
            {
                "year": 2015,
                "median_slope": 0.3958901618476003,
                "median_intercept": 24.5058391900497,
                "x": 26.25757575757568,
                "y": -2.7803030303030103
            },
            {
                "year": 2014,
                "median_slope": 0.9132750452692799,
                "median_intercept": 23.42006671089494,
                "x": 26.462121212121218,
                "y": -1.33333333333329
            },
            {
                "year": 2017,
                "median_slope": -3.5598747657571197,
                "median_intercept": 26.183754218618798,
                "x": 17.26262626262615,
                "y": -0.86363636363635
            },
            {
                "year": 2016,
                "median_slope": -1.41962992792028,
                "median_intercept": 26.61926996832661,
                "x": 24.34848484848485,
                "y": -7.48484848484847
            }
        ]
    },
    {
        "name": "France",
        "years": [
            {
                "year": 2018,
                "median_slope": -3.237315237315238,
                "median_intercept": 19.83418290854572,
                "x": 7.543599723361702,
                "y": -3.427730943326614
            },
            {
                "year": 2019,
                "median_slope": -1.157916788352395,
                "median_intercept": 15.03348889465042,
                "x": 4.011257664478201,
                "y": -1.118077324973859
            },
            {
                "year": 2015,
                "median_slope": 0.3958901618476003,
                "median_intercept": 24.5058391900497,
                "x": 18.27819172684393,
                "y": -1.9439896798573897
            },
            {
                "year": 2014,
                "median_slope": 0.9132750452692799,
                "median_intercept": 23.42006671089494,
                "x": 18.54977131903084,
                "y": 0.36388699486015996
            },
            {
                "year": 2017,
                "median_slope": -3.5598747657571197,
                "median_intercept": 26.183754218618798,
                "x": 12.536283200092702,
                "y": -5.64388300021162
            },
            {
                "year": 2016,
                "median_slope": -1.41962992792028,
                "median_intercept": 26.61926996832661,
                "x": 16.90859635511907,
                "y": -4.69487783409788
            }
        ]
    },
    {
        "name": "Germany",
        "years": [
            {
                "year": 2018,
                "median_slope": -3.237315237315238,
                "median_intercept": 19.83418290854572,
                "x": 6.363614846373501,
                "y": -2.494940753561448
            },
            {
                "year": 2019,
                "median_slope": -1.157916788352395,
                "median_intercept": 15.03348889465042,
                "x": 4.0923682302993,
                "y": -1.8103818103818259
            },
            {
                "year": 2015,
                "median_slope": 0.3958901618476003,
                "median_intercept": 24.5058391900497,
                "x": 11.226376503467,
                "y": -1.2047894445222598
            },
            {
                "year": 2014,
                "median_slope": 0.9132750452692799,
                "median_intercept": 23.42006671089494,
                "x": 11.8967142646015,
                "y": -0.8281988074170101
            },
            {
                "year": 2017,
                "median_slope": -3.5598747657571197,
                "median_intercept": 26.183754218618798,
                "x": 8.234458975838201,
                "y": -1.9147142595418618
            },
            {
                "year": 2016,
                "median_slope": -1.41962992792028,
                "median_intercept": 26.61926996832661,
                "x": 9.938639150304601,
                "y": -1.71631269833765
            }
        ]
    },
    {
        "name": "Greece",
        "years": [
            {
                "year": 2018,
                "median_slope": -3.237315237315238,
                "median_intercept": 19.83418290854572,
                "x": 38.8333333333334,
                "y": -0.9537037037037002
            },
            {
                "year": 2019,
                "median_slope": -1.157916788352395,
                "median_intercept": 15.03348889465042,
                "x": 38.0,
                "y": 0.38888888888889994
            },
            {
                "year": 2015,
                "median_slope": 0.3958901618476003,
                "median_intercept": 24.5058391900497,
                "x": 43.571269664706804,
                "y": -1.5044626304359396
            },
            {
                "year": 2014,
                "median_slope": 0.9132750452692799,
                "median_intercept": 23.42006671089494,
                "x": 44.2618650352244,
                "y": -0.7517788724685301
            },
            {
                "year": 2017,
                "median_slope": -3.5598747657571197,
                "median_intercept": 26.183754218618798,
                "x": 40.333034647550704,
                "y": -2.7150537634408667
            },
            {
                "year": 2016,
                "median_slope": -1.41962992792028,
                "median_intercept": 26.61926996832661,
                "x": 42.4816771721667,
                "y": -1.320263255469045
            }
        ]
    },
    {
        "name": "Hungary",
        "years": [
            {
                "year": 2018,
                "median_slope": -3.237315237315238,
                "median_intercept": 19.83418290854572,
                "x": 22.952075702075707,
                "y": -4.89835164835165
            },
            {
                "year": 2019,
                "median_slope": -1.157916788352395,
                "median_intercept": 15.03348889465042,
                "x": 17.04914529914528,
                "y": 0.025641025641010007
            },
            {
                "year": 2015,
                "median_slope": 0.3958901618476003,
                "median_intercept": 24.5058391900497,
                "x": 24.5058391900497,
                "y": 4.200869306132461
            },
            {
                "year": 2014,
                "median_slope": 0.9132750452692799,
                "median_intercept": 23.42006671089494,
                "x": 20.7456870614766,
                "y": 4.4144744144744195
            },
            {
                "year": 2017,
                "median_slope": -3.5598747657571197,
                "median_intercept": 26.183754218618798,
                "x": 25.864597390913122,
                "y": -5.8590707538076
            },
            {
                "year": 2016,
                "median_slope": -1.41962992792028,
                "median_intercept": 26.61926996832661,
                "x": 28.53685495790764,
                "y": -2.50684403315983
            }
        ]
    },
    {
        "name": "Ireland",
        "years": [
            {
                "year": 2018,
                "median_slope": -3.237315237315238,
                "median_intercept": 19.83418290854572,
                "x": 5.8333333333333,
                "y": -0.65476190476189
            },
            {
                "year": 2019,
                "median_slope": -1.157916788352395,
                "median_intercept": 15.03348889465042,
                "x": 6.0714285714285,
                "y": -1.428571428571423
            },
            {
                "year": 2015,
                "median_slope": 0.3958901618476003,
                "median_intercept": 24.5058391900497,
                "x": 5.873015873015799,
                "y": -1.4285714285714195
            },
            {
                "year": 2014,
                "median_slope": 0.9132750452692799,
                "median_intercept": 23.42006671089494,
                "x": 8.2539682539683,
                "y": -3.0158730158730003
            },
            {
                "year": 2017,
                "median_slope": -3.5598747657571197,
                "median_intercept": 26.183754218618798,
                "x": 5.535714285714203,
                "y": 0.23809523809525013
            },
            {
                "year": 2016,
                "median_slope": -1.41962992792028,
                "median_intercept": 26.61926996832661,
                "x": 3.2738095238096,
                "y": 2.67857142857143
            }
        ]
    },
    {
        "name": "Israel",
        "years": [
            {
                "year": 2018,
                "median_slope": -3.237315237315238,
                "median_intercept": 19.83418290854572,
                "x": 15.13945578231293,
                "y": -7.4557823129251695
            },
            {
                "year": 2019,
                "median_slope": -1.157916788352395,
                "median_intercept": 15.03348889465042,
                "x": 8.031746031746,
                "y": -4.27777777777779
            },
            {
                "year": 2015,
                "median_slope": 0.3958901618476003,
                "median_intercept": 24.5058391900497,
                "x": 24.32314628091023,
                "y": 0.11787529240945993
            },
            {
                "year": 2014,
                "median_slope": 0.9132750452692799,
                "median_intercept": 23.42006671089494,
                "x": 23.56688715011703,
                "y": 1.04504584442473
            },
            {
                "year": 2017,
                "median_slope": -3.5598747657571197,
                "median_intercept": 26.183754218618798,
                "x": 20.383116883116813,
                "y": -6.4763966192537605
            },
            {
                "year": 2016,
                "median_slope": -1.41962992792028,
                "median_intercept": 26.61926996832661,
                "x": 24.26676973819835,
                "y": -3.83254998969284
            }
        ]
    },
    {
        "name": "Italy",
        "years": [
            {
                "year": 2018,
                "median_slope": -3.237315237315238,
                "median_intercept": 19.83418290854572,
                "x": 33.58313020905193,
                "y": -5.66943886597886
            },
            {
                "year": 2019,
                "median_slope": -1.157916788352395,
                "median_intercept": 15.03348889465042,
                "x": 26.96652665143871,
                "y": -1.926262053318216
            },
            {
                "year": 2015,
                "median_slope": 0.3958901618476003,
                "median_intercept": 24.5058391900497,
                "x": 32.82633632122736,
                "y": 4.807115333331041
            },
            {
                "year": 2014,
                "median_slope": 0.9132750452692799,
                "median_intercept": 23.42006671089494,
                "x": 29.733708035258736,
                "y": 3.469081282347722
            },
            {
                "year": 2017,
                "median_slope": -3.5598747657571197,
                "median_intercept": 26.183754218618798,
                "x": 36.0453174497417,
                "y": -3.92429586530552
            },
            {
                "year": 2016,
                "median_slope": -1.41962992792028,
                "median_intercept": 26.61926996832661,
                "x": 36.0010373557065,
                "y": -1.1319229930751589
            }
        ]
    },
    {
        "name": "Japan",
        "years": [
            {
                "year": 2018,
                "median_slope": -3.237315237315238,
                "median_intercept": 19.83418290854572,
                "x": 1.0714285714286014,
                "y": -0.3571428571428501
            },
            {
                "year": 2019,
                "median_slope": -1.157916788352395,
                "median_intercept": 15.03348889465042,
                "x": 0.8333333333333002,
                "y": -0.47619047619048005
            },
            {
                "year": 2015,
                "median_slope": 0.3958901618476003,
                "median_intercept": 24.5058391900497,
                "x": 0.11904761904759908,
                "y": 0.3571428571428701
            },
            {
                "year": 2014,
                "median_slope": 0.9132750452692799,
                "median_intercept": 23.42006671089494,
                "x": 0.0,
                "y": 9.769962616701378e-15
            },
            {
                "year": 2017,
                "median_slope": -3.5598747657571197,
                "median_intercept": 26.183754218618798,
                "x": 0.7142857142856016,
                "y": 0.3571428571428603
            },
            {
                "year": 2016,
                "median_slope": -1.41962992792028,
                "median_intercept": 26.61926996832661,
                "x": 0.3571428571429003,
                "y": 0.47619047619048693
            }
        ]
    },
    {
        "name": "Kuwait",
        "years": [
            {
                "year": 2018,
                "median_slope": -3.237315237315238,
                "median_intercept": 19.83418290854572,
                "x": 19.83418290854572,
                "y": -0.8129345583618401
            },
            {
                "year": 2019,
                "median_slope": -1.157916788352395,
                "median_intercept": 15.03348889465042,
                "x": 18.59186560565869,
                "y": 0.020512820512810004
            },
            {
                "year": 2015,
                "median_slope": 0.3958901618476003,
                "median_intercept": 24.5058391900497,
                "x": 19.67309602399113,
                "y": 0.7908682016098803
            },
            {
                "year": 2014,
                "median_slope": 0.9132750452692799,
                "median_intercept": 23.42006671089494,
                "x": 19.53114927130278,
                "y": 0.07763569195793973
            },
            {
                "year": 2017,
                "median_slope": -3.5598747657571197,
                "median_intercept": 26.183754218618798,
                "x": 20.218790238580283,
                "y": -0.5903026508723799
            },
            {
                "year": 2016,
                "median_slope": -1.41962992792028,
                "median_intercept": 26.61926996832661,
                "x": 19.63465788473288,
                "y": -0.03417997960727304
            }
        ]
    },
    {
        "name": "Mexico",
        "years": [
            {
                "year": 2018,
                "median_slope": -3.237315237315238,
                "median_intercept": 19.83418290854572,
                "x": 18.68858191991607,
                "y": -8.6172796331915
            },
            {
                "year": 2019,
                "median_slope": -1.157916788352395,
                "median_intercept": 15.03348889465042,
                "x": 10.31778412439367,
                "y": -5.068226120857711
            },
            {
                "year": 2015,
                "median_slope": 0.3958901618476003,
                "median_intercept": 24.5058391900497,
                "x": 26.86024292758036,
                "y": 2.9983690844758843
            },
            {
                "year": 2014,
                "median_slope": 0.9132750452692799,
                "median_intercept": 23.42006671089494,
                "x": 23.42006671089494,
                "y": 5.40288220551379
            },
            {
                "year": 2017,
                "median_slope": -3.5598747657571197,
                "median_intercept": 26.183754218618798,
                "x": 26.55594755241952,
                "y": -8.49062350358341
            },
            {
                "year": 2016,
                "median_slope": -1.41962992792028,
                "median_intercept": 26.61926996832661,
                "x": 29.999573717696002,
                "y": -4.78451962860488
            }
        ]
    },
    {
        "name": "Netherlands",
        "years": [
            {
                "year": 2018,
                "median_slope": -3.237315237315238,
                "median_intercept": 19.83418290854572,
                "x": 8.425213675213701,
                "y": 0.8685897435897396
            },
            {
                "year": 2019,
                "median_slope": -1.157916788352395,
                "median_intercept": 15.03348889465042,
                "x": 9.3611111111111,
                "y": -0.11111111111112004
            },
            {
                "year": 2015,
                "median_slope": 0.3958901618476003,
                "median_intercept": 24.5058391900497,
                "x": 5.072217675941101,
                "y": 0.3958901618476003
            },
            {
                "year": 2014,
                "median_slope": 0.9132750452692799,
                "median_intercept": 23.42006671089494,
                "x": 5.204105291871297,
                "y": -0.5508501545735602
            },
            {
                "year": 2017,
                "median_slope": -3.5598747657571197,
                "median_intercept": 26.183754218618798,
                "x": 6.5566239316239034,
                "y": 2.32478632478632
            },
            {
                "year": 2016,
                "median_slope": -1.41962992792028,
                "median_intercept": 26.61926996832661,
                "x": 5.199786324786402,
                "y": 1.43803418803418
            }
        ]
    },
    {
        "name": "Philippines",
        "years": [
            {
                "year": 2018,
                "median_slope": -3.237315237315238,
                "median_intercept": 19.83418290854572,
                "x": 19.92429792429791,
                "y": -3.5054945054945
            },
            {
                "year": 2019,
                "median_slope": -1.157916788352395,
                "median_intercept": 15.03348889465042,
                "x": 15.934065934065888,
                "y": -0.879120879120875
            },
            {
                "year": 2015,
                "median_slope": 0.3958901618476003,
                "median_intercept": 24.5058391900497,
                "x": 34.167046575715304,
                "y": -1.4084078975719998
            },
            {
                "year": 2014,
                "median_slope": 0.9132750452692799,
                "median_intercept": 23.42006671089494,
                "x": 32.3048344844011,
                "y": 3.98462974933563
            },
            {
                "year": 2017,
                "median_slope": -3.5598747657571197,
                "median_intercept": 26.183754218618798,
                "x": 27.75599254546617,
                "y": -7.67444251654779
            },
            {
                "year": 2016,
                "median_slope": -1.41962992792028,
                "median_intercept": 26.61926996832661,
                "x": 34.917758196396036,
                "y": -8.46733349210131
            }
        ]
    },
    {
        "name": "Poland",
        "years": [
            {
                "year": 2018,
                "median_slope": -3.237315237315238,
                "median_intercept": 19.83418290854572,
                "x": 23.556876471096615,
                "y": -8.32236524373815
            },
            {
                "year": 2019,
                "median_slope": -1.157916788352395,
                "median_intercept": 15.03348889465042,
                "x": 15.03348889465042,
                "y": -3.1620718462823802
            },
            {
                "year": 2015,
                "median_slope": 0.3958901618476003,
                "median_intercept": 24.5058391900497,
                "x": 35.0309730683445,
                "y": 1.3035453909917
            },
            {
                "year": 2014,
                "median_slope": 0.9132750452692799,
                "median_intercept": 23.42006671089494,
                "x": 33.2826059456041,
                "y": 3.0757326586548537
            },
            {
                "year": 2017,
                "median_slope": -3.5598747657571197,
                "median_intercept": 26.183754218618798,
                "x": 31.66787997715718,
                "y": -10.20175014954562
            },
            {
                "year": 2016,
                "median_slope": -1.41962992792028,
                "median_intercept": 26.61926996832661,
                "x": 35.8350902447508,
                "y": -5.02593869349157
            }
        ]
    },
    {
        "name": "Portugal",
        "years": [
            {
                "year": 2018,
                "median_slope": -3.237315237315238,
                "median_intercept": 19.83418290854572,
                "x": 39.7029908737689,
                "y": -5.05520918044638
            },
            {
                "year": 2019,
                "median_slope": -1.157916788352395,
                "median_intercept": 15.03348889465042,
                "x": 35.7449173217674,
                "y": -5.0056925996205095
            },
            {
                "year": 2015,
                "median_slope": 0.3958901618476003,
                "median_intercept": 24.5058391900497,
                "x": 35.815888287936204,
                "y": 3.194579857278207
            },
            {
                "year": 2014,
                "median_slope": 0.9132750452692799,
                "median_intercept": 23.42006671089494,
                "x": 33.307114848716,
                "y": 2.214121594000667
            },
            {
                "year": 2017,
                "median_slope": -3.5598747657571197,
                "median_intercept": 26.183754218618798,
                "x": 39.099232574008404,
                "y": 0.28330575834338
            },
            {
                "year": 2016,
                "median_slope": -1.41962992792028,
                "median_intercept": 26.61926996832661,
                "x": 39.2861675174049,
                "y": 1.06155034958281
            }
        ]
    },
    {
        "name": "South Africa",
        "years": [
            {
                "year": 2018,
                "median_slope": -3.237315237315238,
                "median_intercept": 19.83418290854572,
                "x": 46.8131313131313,
                "y": -1.1010101010100999
            },
            {
                "year": 2019,
                "median_slope": -1.157916788352395,
                "median_intercept": 15.03348889465042,
                "x": 46.996632996633,
                "y": -2.335016835016834
            },
            {
                "year": 2015,
                "median_slope": 0.3958901618476003,
                "median_intercept": 24.5058391900497,
                "x": 25.38888888888887,
                "y": 9.59259259259259
            },
            {
                "year": 2014,
                "median_slope": 0.9132750452692799,
                "median_intercept": 23.42006671089494,
                "x": 20.277777777777843,
                "y": 5.83333333333333
            },
            {
                "year": 2017,
                "median_slope": -3.5598747657571197,
                "median_intercept": 26.183754218618798,
                "x": 42.3080808080808,
                "y": 3.59090909090909
            },
            {
                "year": 2016,
                "median_slope": -1.41962992792028,
                "median_intercept": 26.61926996832661,
                "x": 33.851851851851904,
                "y": 9.42592592592592
            }
        ]
    },
    {
        "name": "Spain",
        "years": [
            {
                "year": 2018,
                "median_slope": -3.237315237315238,
                "median_intercept": 19.83418290854572,
                "x": 20.812786247568862,
                "y": -5.15606374302026
            },
            {
                "year": 2019,
                "median_slope": -1.157916788352395,
                "median_intercept": 15.03348889465042,
                "x": 16.404793274358468,
                "y": -3.4209799861973798
            },
            {
                "year": 2015,
                "median_slope": 0.3958901618476003,
                "median_intercept": 24.5058391900497,
                "x": 24.45485560285627,
                "y": 2.261129890695404
            },
            {
                "year": 2014,
                "median_slope": 0.9132750452692799,
                "median_intercept": 23.42006671089494,
                "x": 22.466389456522798,
                "y": 3.68804691740472
            },
            {
                "year": 2017,
                "median_slope": -3.5598747657571197,
                "median_intercept": 26.183754218618798,
                "x": 26.183754218618798,
                "y": -5.84315320082343
            },
            {
                "year": 2016,
                "median_slope": -1.41962992792028,
                "median_intercept": 26.61926996832661,
                "x": 26.61926996832661,
                "y": -1.187957744561525
            }
        ]
    },
    {
        "name": "Switzerland",
        "years": [
            {
                "year": 2018,
                "median_slope": -3.237315237315238,
                "median_intercept": 19.83418290854572,
                "x": 0.0,
                "y": 1.021405182655144e-14
            },
            {
                "year": 2019,
                "median_slope": -1.157916788352395,
                "median_intercept": 15.03348889465042,
                "x": 0.0,
                "y": 9.992007221626409e-15
            },
            {
                "year": 2015,
                "median_slope": 0.3958901618476003,
                "median_intercept": 24.5058391900497,
                "x": 0.0,
                "y": 1.021405182655144e-14
            },
            {
                "year": 2014,
                "median_slope": 0.9132750452692799,
                "median_intercept": 23.42006671089494,
                "x": 9.947598300641403e-14,
                "y": 9.769962616701378e-15
            },
            {
                "year": 2017,
                "median_slope": -3.5598747657571197,
                "median_intercept": 26.183754218618798,
                "x": -9.947598300641403e-14,
                "y": 1.9984014443252818e-14
            },
            {
                "year": 2016,
                "median_slope": -1.41962992792028,
                "median_intercept": 26.61926996832661,
                "x": 0.0,
                "y": 6.994405055138486e-15
            }
        ]
    },
    {
        "name": "Taiwan",
        "years": [
            {
                "year": 2018,
                "median_slope": -3.237315237315238,
                "median_intercept": 19.83418290854572,
                "x": 22.685826591708953,
                "y": 1.11772018830843
            },
            {
                "year": 2019,
                "median_slope": -1.157916788352395,
                "median_intercept": 15.03348889465042,
                "x": 22.37409997409996,
                "y": 2.9306397306397303
            },
            {
                "year": 2015,
                "median_slope": 0.3958901618476003,
                "median_intercept": 24.5058391900497,
                "x": 29.60296485744054,
                "y": -1.23515203182723
            },
            {
                "year": 2014,
                "median_slope": 0.9132750452692799,
                "median_intercept": 23.42006671089494,
                "x": 30.018471156578638,
                "y": 0.6365444728616099
            },
            {
                "year": 2017,
                "median_slope": -3.5598747657571197,
                "median_intercept": 26.183754218618798,
                "x": 26.42063165592571,
                "y": -3.5598747657571197
            },
            {
                "year": 2016,
                "median_slope": -1.41962992792028,
                "median_intercept": 26.61926996832661,
                "x": 28.05113996546226,
                "y": -3.8130952120722
            }
        ]
    },
    {
        "name": "Thailand",
        "years": [
            {
                "year": 2018,
                "median_slope": -3.237315237315238,
                "median_intercept": 19.83418290854572,
                "x": 41.96767676767681,
                "y": -11.18787878787878
            },
            {
                "year": 2019,
                "median_slope": -1.157916788352395,
                "median_intercept": 15.03348889465042,
                "x": 30.5656565656565,
                "y": -4.2020202020202
            },
            {
                "year": 2015,
                "median_slope": 0.3958901618476003,
                "median_intercept": 24.5058391900497,
                "x": 39.3186026936026,
                "y": 11.35858585858585
            },
            {
                "year": 2014,
                "median_slope": 0.9132750452692799,
                "median_intercept": 23.42006671089494,
                "x": 31.6140572390573,
                "y": 11.15109427609429
            },
            {
                "year": 2017,
                "median_slope": -3.5598747657571197,
                "median_intercept": 26.183754218618798,
                "x": 50.8525252525252,
                "y": -12.33131313131314
            },
            {
                "year": 2016,
                "median_slope": -1.41962992792028,
                "median_intercept": 26.61926996832661,
                "x": 48.457575757575796,
                "y": 0.252777777777773
            }
        ]
    },
    {
        "name": "Turkey",
        "years": [
            {
                "year": 2018,
                "median_slope": -3.237315237315238,
                "median_intercept": 19.83418290854572,
                "x": 35.0683703078385,
                "y": -3.59657811847575
            },
            {
                "year": 2019,
                "median_slope": -1.157916788352395,
                "median_intercept": 15.03348889465042,
                "x": 31.4135751199704,
                "y": -1.5799187892211186
            },
            {
                "year": 2015,
                "median_slope": 0.3958901618476003,
                "median_intercept": 24.5058391900497,
                "x": 38.6862596231348,
                "y": 2.171357647417217
            },
            {
                "year": 2014,
                "median_slope": 0.9132750452692799,
                "median_intercept": 23.42006671089494,
                "x": 35.9569267531083,
                "y": 4.22402467584395
            },
            {
                "year": 2017,
                "median_slope": -3.5598747657571197,
                "median_intercept": 26.183754218618798,
                "x": 39.2915634133943,
                "y": -4.7163031243759495
            },
            {
                "year": 2016,
                "median_slope": -1.41962992792028,
                "median_intercept": 26.61926996832661,
                "x": 41.5383905961425,
                "y": -2.9189137836928802
            }
        ]
    },
    {
        "name": "United Kingdom",
        "years": [
            {
                "year": 2018,
                "median_slope": -3.237315237315238,
                "median_intercept": 19.83418290854572,
                "x": 19.629629629629633,
                "y": -10.55555555555556
            },
            {
                "year": 2019,
                "median_slope": -1.157916788352395,
                "median_intercept": 15.03348889465042,
                "x": 10.55555555555555,
                "y": -7.22222222222223
            },
            {
                "year": 2015,
                "median_slope": 0.3958901618476003,
                "median_intercept": 24.5058391900497,
                "x": 15.82592592592591,
                "y": 7.64907407407407
            },
            {
                "year": 2014,
                "median_slope": 0.9132750452692799,
                "median_intercept": 23.42006671089494,
                "x": 11.347222222222278,
                "y": 6.01851851851852
            },
            {
                "year": 2017,
                "median_slope": -3.5598747657571197,
                "median_intercept": 26.183754218618798,
                "x": 24.585185185185132,
                "y": -7.09629629629631
            },
            {
                "year": 2016,
                "median_slope": -1.41962992792028,
                "median_intercept": 26.61926996832661,
                "x": 21.68148148148152,
                "y": 2.82222222222222
            }
        ]
    },
    {
        "name": "United States",
        "years": [
            {
                "year": 2018,
                "median_slope": -3.237315237315238,
                "median_intercept": 19.83418290854572,
                "x": 6.278380386506903,
                "y": -1.38616051650166
            },
            {
                "year": 2019,
                "median_slope": -1.157916788352395,
                "median_intercept": 15.03348889465042,
                "x": 5.320009549334399,
                "y": -1.157916788352395
            },
            {
                "year": 2015,
                "median_slope": 0.3958901618476003,
                "median_intercept": 24.5058391900497,
                "x": 4.4407419051464,
                "y": 1.08234649951217
            },
            {
                "year": 2014,
                "median_slope": 0.9132750452692799,
                "median_intercept": 23.42006671089494,
                "x": 4.323979635356899,
                "y": 0.09238665526092005
            },
            {
                "year": 2017,
                "median_slope": -3.5598747657571197,
                "median_intercept": 26.183754218618798,
                "x": 6.360906651850701,
                "y": -0.5353963292306299
            },
            {
                "year": 2016,
                "median_slope": -1.41962992792028,
                "median_intercept": 26.61926996832661,
                "x": 4.847246096747099,
                "y": 1.7180477253664201
            }
        ]
    },
    {
        "name": "Venezuela",
        "years": [
            {
                "year": 2018,
                "median_slope": -3.237315237315238,
                "median_intercept": 19.83418290854572,
                "x": 10.660660660660701,
                "y": -6.6066066066066
            },
            {
                "year": 2019,
                "median_slope": -1.157916788352395,
                "median_intercept": 15.03348889465042,
                "x": 4.4444444444443985,
                "y": -3.33333333333334
            },
            {
                "year": 2015,
                "median_slope": 0.3958901618476003,
                "median_intercept": 24.5058391900497,
                "x": 20.59009009009007,
                "y": -1.0375375375375397
            },
            {
                "year": 2014,
                "median_slope": 0.9132750452692799,
                "median_intercept": 23.42006671089494,
                "x": 21.642642642642702,
                "y": -0.9504504504504503
            },
            {
                "year": 2017,
                "median_slope": -3.5598747657571197,
                "median_intercept": 26.183754218618798,
                "x": 16.12612612612606,
                "y": -7.02702702702703
            },
            {
                "year": 2016,
                "median_slope": -1.41962992792028,
                "median_intercept": 26.61926996832661,
                "x": 18.37837837837841,
                "y": -2.40990990990991
            }
        ]
    }
]